beadpull/__init__.py
beadpull/__main__.py
beadpull/logging.yaml
beadpull/version.py
beadpull/analyzer/__init__.py
beadpull/analyzer/analyzer.py
beadpull/analyzer/defaults.yaml
beadpull/analyzer/fake.py
beadpull/analyzer/generic.py
beadpull/analyzer/randomly_failing.py
beadpull/analyzer/agilent8753et/__init__.py
beadpull/analyzer/agilent8753et/agilent8753et.py
beadpull/analyzer/agilent8753et/agilent8753et_binding.py
beadpull/analyzer/agilent8753et/datadecoder.py
beadpull/analyzer/agilent8753et/settings.yaml
beadpull/analyzer/common/mgpib.py
beadpull/doc/doc.html
beadpull/doc/doc.md
beadpull/equation/__init__.py
beadpull/equation/defaults.yaml
beadpull/equation/equation.py
beadpull/icon/icon.ico
beadpull/icon/icon.svg
beadpull/motor/__init__.py
beadpull/motor/defaults.yaml
beadpull/motor/fake.py
beadpull/motor/generic.py
beadpull/motor/motor.py
beadpull/motor/randomly_failing.py
beadpull/motor/common/mserial.py
beadpull/motor/uirobot/__init__.py
beadpull/motor/uirobot/convertbinary.py
beadpull/motor/uirobot/settings.yaml
beadpull/motor/uirobot/uirobot.py
beadpull/motor/uirobot/uirobot_binding.py
beadpull/ui/__init__.py
beadpull/ui/alert.ui
beadpull/ui/calibrate.ui
beadpull/ui/defaults.yaml
beadpull/ui/loadsettings.py
beadpull/ui/support.py
beadpull/ui/window.py
beadpull/ui/window.ui
beadpull-19.10.dist-info/LICENSE
beadpull-19.10.dist-info/METADATA
beadpull-19.10.dist-info/WHEEL
beadpull-19.10.dist-info/entry_points.txt
beadpull-19.10.dist-info/top_level.txt
beadpull-19.10.dist-info/RECORD
