Metadata-Version: 2.1
Name: beadpull
Version: 19.10
Summary: Bead pulling measurement software for RF cavity measurements
Home-page: https://gitlab.com/matsievskiysv/beadpull
Author: S.V. Matsievskiy
Author-email: matsievskiysv@gmail.com
Maintainer: S.V. Matsievskiy
Maintainer-email: matsievskiysv@gmail.com
License: GPLv3+
Keywords: accelerators particles measurements
Platform: UNKNOWN
Classifier: Development Status :: 5 - Production/Stable
Classifier: Environment :: X11 Applications :: Qt
Classifier: Intended Audience :: End Users/Desktop
Classifier: License :: OSI Approved :: GNU General Public License v3 or later (GPLv3+)
Classifier: Operating System :: OS Independent
Classifier: Programming Language :: Python :: 3.5
Classifier: Topic :: Scientific/Engineering :: Physics
Requires-Dist: PyQt5
Requires-Dist: PyQtWebEngine
Requires-Dist: PyVISA
Requires-Dist: PyYAML
Requires-Dist: matplotlib
Requires-Dist: numpy
Requires-Dist: pysmithplot-fork
Requires-Dist: pyvisa-py
Provides-Extra: dev
Requires-Dist: check-manifest ; extra == 'dev'
